alibabacloud_alb20200616/__init__.py
alibabacloud_alb20200616/client.py
alibabacloud_alb20200616/models/__init__.py
alibabacloud_alb20200616/models/_add_entries_to_acl_request.py
alibabacloud_alb20200616/models/_add_entries_to_acl_response.py
alibabacloud_alb20200616/models/_add_entries_to_acl_response_body.py
alibabacloud_alb20200616/models/_add_servers_to_server_group_request.py
alibabacloud_alb20200616/models/_add_servers_to_server_group_response.py
alibabacloud_alb20200616/models/_add_servers_to_server_group_response_body.py
alibabacloud_alb20200616/models/_apply_health_check_template_to_server_group_request.py
alibabacloud_alb20200616/models/_apply_health_check_template_to_server_group_response.py
alibabacloud_alb20200616/models/_apply_health_check_template_to_server_group_response_body.py
alibabacloud_alb20200616/models/_associate_acls_with_listener_request.py
alibabacloud_alb20200616/models/_associate_acls_with_listener_response.py
alibabacloud_alb20200616/models/_associate_acls_with_listener_response_body.py
alibabacloud_alb20200616/models/_associate_additional_certificates_with_listener_request.py
alibabacloud_alb20200616/models/_associate_additional_certificates_with_listener_response.py
alibabacloud_alb20200616/models/_associate_additional_certificates_with_listener_response_body.py
alibabacloud_alb20200616/models/_attach_common_bandwidth_package_to_load_balancer_request.py
alibabacloud_alb20200616/models/_attach_common_bandwidth_package_to_load_balancer_response.py
alibabacloud_alb20200616/models/_attach_common_bandwidth_package_to_load_balancer_response_body.py
alibabacloud_alb20200616/models/_cancel_shift_load_balancer_zones_request.py
alibabacloud_alb20200616/models/_cancel_shift_load_balancer_zones_response.py
alibabacloud_alb20200616/models/_cancel_shift_load_balancer_zones_response_body.py
alibabacloud_alb20200616/models/_create_acl_request.py
alibabacloud_alb20200616/models/_create_acl_response.py
alibabacloud_alb20200616-1.3.1.dist-info/LICENSE
alibabacloud_alb20200616-1.3.1.dist-info/METADATA
alibabacloud_alb20200616-1.3.1.dist-info/WHEEL
alibabacloud_alb20200616-1.3.1.dist-info/top_level.txt
alibabacloud_alb20200616-1.3.1.dist-info/RECORD
